{"id": "77054a17-7279-4ca0-a0e5-c762dac20700", "client_id": "asdfasdf", "status": "completed", "message": "Completed", "results": [{"row": 2, "symbol": "SENSEX 18 DEC 85000 PUT", "status": "Failed", "message": "Order error: Symbol 'SENSEX 18 DEC 85000 PUT' not found in Dhan instruments", "order_id": null}, {"row": 3, "symbol": "SENSEX 18 DEC 84900 PUT", "status": "Failed", "message": "Order error: Symbol 'SENSEX 18 DEC 84900 PUT' not found in Dhan instruments", "order_id": null}, {"row": 4, "symbol": "SENSEX 18 DEC 84800 PUT", "status": "Failed", "message": "Order error: Symbol 'SENSEX 18 DEC 84800 PUT' not found in Dhan instruments", "order_id": null}, {"row": 5, "symbol": "SENSEX 18 DEC 84700 PUT", "status": "Failed", "message": "Order error: Symbol 'SENSEX 18 DEC 84700 PUT' not found in Dhan instruments", "order_id": null}, {"row": 6, "symbol": "SENSEX 18 DEC 84600 PUT", "status": "Failed", "message": "Order error: Symbol 'SENSEX 18 DEC 84600 PUT' not found in Dhan instruments", "order_id": null}], "success_count": 0, "failed_count": 5, "total": 5, "started_at": "2025-12-22T21:36:15.311806", "finished_at": "2025-12-22T21:36:15.313163", "error": null, "perf": {"prefetch_s": 0.0, "orders_seen": 5, "build_s_total": 4.090000220458023e-05, "rate_wait_s_total": 9.20000093174167e-06, "api_s_total": 0.00011960000483668409, "row_s_total": 0.00019590000010794029, "avg_build_s": 0.0, "avg_rate_wait_s": 0.0, "avg_api_s": 0.0, "avg_row_s": 0.0}}